{"inkVersion":21,"root":[["ev","str","^??","/str","/ev",{"VAR=":"NPCName","re":true},"^< Turning to the door, you can't help a smile creeping across your face as you recognize who has just walked in. >","\n","ev","str","^-Continue-","/str","/ev",{"*":"0.c-0","flg":20},{"c-0":["\n","ev","str","^Rowan","/str","/ev",{"VAR=":"NPCName","re":true},{"->":"0.g-0"},{"#f":5}],"g-0":["^It's so good to see you! Been way too long!","\n","ev","str","^-End Game-","/str","/ev",{"*":".^.c-1","flg":20},{"c-1":["^ ","end","\n",{"->":"0.g-1"},{"#f":5}],"#f":5}],"g-1":["done",{"#f":5}]}],"done",{"global decl":["ev","str","^??","/str",{"VAR=":"NPCName"},"/ev","end",null],"#f":1}],"listDefs":{}}